soraxas_toolbox/__init__.py
soraxas_toolbox/easy_with_blocks.py
soraxas_toolbox/globals.py
soraxas_toolbox/image.py
soraxas_toolbox/meta.py
soraxas_toolbox/notebook.py
soraxas_toolbox/stats.py
soraxas_toolbox/test_image.py
soraxas_toolbox/_core/__init__.py
soraxas_toolbox/_core/core.py
soraxas_toolbox/_core/csv_logging.py
soraxas_toolbox/_core/performance_timing.py
soraxas_toolbox/_core/plotting.py
soraxas_toolbox/_core/utils.py
soraxas_toolbox/torch/__init__.py
soraxas_toolbox/torch/bitwise.py
soraxas_toolbox/torch/checkpointer.py
soraxas_toolbox/torch/dataloading.py
soraxas_toolbox/torch/image_processing.py
soraxas_toolbox/torch/misc.py
soraxas_toolbox/torch/network_printer.py
soraxas_toolbox-0.1.6.dist-info/LICENSE
soraxas_toolbox-0.1.6.dist-info/METADATA
soraxas_toolbox-0.1.6.dist-info/WHEEL
soraxas_toolbox-0.1.6.dist-info/top_level.txt
soraxas_toolbox-0.1.6.dist-info/RECORD
