Metadata-Version: 2.1
Name: soraxas_toolbox
Version: 0.1.6
Summary: A simple packaged toolbox for various scenario
Home-page: https://github.com/soraxas/pytoolbox
Author: soraxas
Author-email: oscar@tinyiu.com
Classifier: Programming Language :: Python :: 3
Classifier: License :: OSI Approved :: MIT License
Classifier: Operating System :: OS Independent
License-File: LICENSE
Requires-Dist: pip-ensure-version >=1.0.1
